README.md
setup.py
net_score/__init__.py
net_score/main.py
net_score.egg-info/PKG-INFO
net_score.egg-info/SOURCES.txt
net_score.egg-info/dependency_links.txt
net_score.egg-info/requires.txt
net_score.egg-info/top_level.txt